yanhekt/__init__.py
yanhekt/gui.py
yanhekt/m3u8dl.py
yanhekt/main.py
yanhekt/yanhekt.py
yanhekt-2.3.4.dist-info/LICENSE
yanhekt-2.3.4.dist-info/METADATA
yanhekt-2.3.4.dist-info/WHEEL
yanhekt-2.3.4.dist-info/entry_points.txt
yanhekt-2.3.4.dist-info/top_level.txt
yanhekt-2.3.4.dist-info/RECORD
