Metadata-Version: 2.1
Name: yanhekt
Version: 2.3.4
Summary: Download Videos on BIT YanHeKT
Author-email: GDDG08 <ZZH-Fusion@outlook.com>
License: Mozilla Public License Version 2.0
Project-URL: Homepage, https://github.com/GDDG08/YanHeKT_Downloader
Project-URL: Issues, https://github.com/GDDG08/YanHeKT_Downloader/issues
Keywords: yanhekt,bit
Classifier: Development Status :: 4 - Beta
Classifier: Programming Language :: Python :: 3
License-File: LICENSE
Requires-Dist: requests
Requires-Dist: PySimpleGUI <=4.55.1
